upstox_auto_login/__init__.py
upstox_auto_login/core.py
upstox_fastaccess-0.1.6.dist-info/METADATA
upstox_fastaccess-0.1.6.dist-info/WHEEL
upstox_fastaccess-0.1.6.dist-info/top_level.txt
upstox_fastaccess-0.1.6.dist-info/RECORD
