Metadata-Version: 2.4
Name: upstox-fastaccess
Version: 0.1.6
Summary: A lightweight automation tool to securely and quickly log in to your Upstox account.
Author-email: Uttam <uttamraj5050@gmail.com>
License: MIT
Project-URL: Homepage, https://github.com/uttam04/upstox-auto-login
Requires-Python: >=3.10
Requires-Dist: selenium>=4.0
Requires-Dist: pyotp
Requires-Dist: requests
Requires-Dist: pandas
